[{"domain": ".x.com", "expiry": 1750836262, "httpOnly": false, "name": "guest_id_marketing", "path": "/", "sameSite": "None", "secure": true, "value": "v1%3A171626139643519547"}, {"domain": ".x.com", "expiry": 1747812259, "httpOnly": false, "name": "night_mode", "path": "/", "sameSite": "None", "secure": true, "value": "2"}, {"domain": ".x.com", "expiry": 1716285228, "httpOnly": false, "name": "gt", "path": "/", "sameSite": "Lax", "secure": true, "value": "1792818557744755096"}, {"domain": ".x.com", "expiry": 1750836262, "httpOnly": false, "name": "guest_id_ads", "path": "/", "sameSite": "None", "secure": true, "value": "v1%3A171626139643519547"}, {"domain": "x.com", "httpOnly": false, "name": "lang", "path": "/", "sameSite": "Lax", "secure": false, "value": "en"}, {"domain": ".x.com", "expiry": 1747812262, "httpOnly": false, "name": "twid", "path": "/", "sameSite": "None", "secure": true, "value": "u%3D1786430839745605633"}, {"domain": ".x.com", "expiry": 1750836262, "httpOnly": false, "name": "personalization_id", "path": "/", "sameSite": "None", "secure": true, "value": "\"v1_1doziytGTFYN2xby82A2Mg==\""}, {"domain": ".x.com", "expiry": 1750836286, "httpOnly": false, "name": "_ga", "path": "/", "sameSite": "Lax", "secure": false, "value": "GA1.2.1527070462.1716261427"}, {"domain": ".x.com", "expiry": 1750821512, "httpOnly": true, "name": "kdt", "path": "/", "sameSite": "Lax", "secure": true, "value": "ExtFS8R4Y4UHsOfrchN9yZUeiYfDXwmDjPaEHZuW"}, {"domain": ".x.com", "expiry": 1750821512, "httpOnly": true, "name": "auth_token", "path": "/", "sameSite": "None", "secure": true, "value": "4ec7b9b63d704fb280965ccb7100837ab74defc7"}, {"domain": ".x.com", "httpOnly": false, "name": "lang", "path": "/", "sameSite": "Lax", "secure": true, "value": "en"}, {"domain": ".x.com", "expiry": 1716347913, "httpOnly": true, "name": "att", "path": "/", "sameSite": "None", "secure": true, "value": "1-yJVujwqfHU9ePnaYANuxHK3Jd7ShHA2gWrvTYCPO"}, {"domain": ".x.com", "expiry": 1750821512, "httpOnly": false, "name": "ct0", "path": "/", "sameSite": "Lax", "secure": true, "value": "98d6e480bdc9fc43c4f44959212ddc1fb319fc8537288ad3b36d104c0ba3719d49e9e9e5b32afee5eea1ec0d072dbd2403ab943d5a98546eed804d569184438df20b2f92bc39be48d6c76ee4c6927629"}, {"domain": ".x.com", "expiry": 1747797398, "httpOnly": false, "name": "guest_id", "path": "/", "sameSite": "None", "secure": true, "value": "171626139643519547"}, {"domain": ".x.com", "expiry": 1716362686, "httpOnly": false, "name": "_gid", "path": "/", "sameSite": "Lax", "secure": false, "value": "GA1.2.877411789.1716261427"}]