[{"domain": ".twitter.com", "expiry": 1747297324, "httpOnly": false, "name": "twid", "path": "/", "sameSite": "None", "secure": true, "value": "u%3D1786453680071282688"}, {"domain": ".twitter.com", "expiry": 1750321324, "httpOnly": false, "name": "personalization_id", "path": "/", "sameSite": "None", "secure": true, "value": "\"v1_45NXYp0bXVJTbVN6cziecQ==\""}, {"domain": ".twitter.com", "expiry": 1750321324, "httpOnly": false, "name": "ct0", "path": "/", "sameSite": "Lax", "secure": true, "value": "1932198a9e69d42a568c64a5264891d8b707e392d6e2274cb6a386524ebddf08065d2c3c060efc9d19db1fe332e4465d354568025b950653573bda491adcb975078334619045ab84da78bcdd7b82422e"}, {"domain": ".twitter.com", "expiry": 1750321323, "httpOnly": true, "name": "auth_token", "path": "/", "sameSite": "None", "secure": true, "value": "34dab30e48569b381566ffde1a50f7e67c955a95"}, {"domain": ".twitter.com", "expiry": 1750321324, "httpOnly": false, "name": "guest_id_marketing", "path": "/", "sameSite": "None", "secure": true, "value": "v1%3A171576129017678976"}, {"domain": ".twitter.com", "expiry": 1750321335, "httpOnly": false, "name": "_ga", "path": "/", "sameSite": "Lax", "secure": false, "value": "GA1.2.726846401.1715761303"}, {"domain": ".twitter.com", "expiry": 1750321323, "httpOnly": true, "name": "kdt", "path": "/", "sameSite": "Lax", "secure": true, "value": "iXxvJ8HVF8c08elVQdFLyfDtK8LiONI1PLdcYoMN"}, {"domain": "twitter.com", "httpOnly": false, "name": "lang", "path": "/", "sameSite": "Lax", "secure": false, "value": "en"}, {"domain": ".twitter.com", "expiry": 1715770290, "httpOnly": false, "name": "gt", "path": "/", "sameSite": "Lax", "secure": true, "value": "1790658752993271818"}, {"domain": ".twitter.com", "expiry": 1750321290, "httpOnly": false, "name": "guest_id", "path": "/", "sameSite": "None", "secure": true, "value": "v1%3A171576129017678976"}, {"domain": ".twitter.com", "httpOnly": true, "name": "_twitter_sess", "path": "/", "sameSite": "Lax", "secure": true, "value": "BAh7CSIKZmxhc2hJQzonQWN0aW9uQ29udHJvbGxlcjo6Rmxhc2g6OkZsYXNo%250ASGFzaHsABjoKQHVzZWR7ADoPY3JlYXRlZF9hdGwrCDsOWHuPAToMY3NyZl9p%250AZCIlMjhhNWY4ZDU1ZjM4OTlhM2NiZjNhOGFlMTlmYTIxNmM6B2lkIiU1OTcw%250AZDU1NDY5NGE3YmQ2NGYxMzhlYjQxODA3NTQ1NA%253D%253D--85f595f1a91080751a4302ac615a6ec3ce5a880d"}, {"domain": ".twitter.com", "expiry": 1715847735, "httpOnly": false, "name": "_gid", "path": "/", "sameSite": "Lax", "secure": false, "value": "GA1.2.648099105.1715761303"}, {"domain": ".twitter.com", "expiry": 1750321324, "httpOnly": false, "name": "guest_id_ads", "path": "/", "sameSite": "None", "secure": true, "value": "v1%3A171576129017678976"}]